{
    "GoodFellas": {
        "start": "2025-10-25",
        "end": "2025-11-07"
    },
    "Be Vondrsfull": {
        "start": "2025-10-25",
        "end": "2025-11-07"
    },
    "Form Factory F\u00fcgnerova": {
        "start": "2025-10-25",
        "end": "2025-11-02"
    },
    "Profitko": {
        "start": "2025-10-25",
        "end": "2025-11-08"
    },
    "Siddha Yoga": {
        "start": "2025-10-25",
        "end": "2025-11-07"
    },
    "Yogaholick": {
        "start": "2025-10-25",
        "end": "2025-11-07"
    }
}